odoo/addons/stock_replenishment_mrp_bom_selection/README.rst
odoo/addons/stock_replenishment_mrp_bom_selection/__init__.py
odoo/addons/stock_replenishment_mrp_bom_selection/__manifest__.py
odoo/addons/stock_replenishment_mrp_bom_selection/i18n/es.po
odoo/addons/stock_replenishment_mrp_bom_selection/i18n/it.po
odoo/addons/stock_replenishment_mrp_bom_selection/i18n/stock_replenishment_mrp_bom_selection.pot
odoo/addons/stock_replenishment_mrp_bom_selection/models/__init__.py
odoo/addons/stock_replenishment_mrp_bom_selection/models/stock_warehouse_orderpoint.py
odoo/addons/stock_replenishment_mrp_bom_selection/readme/CONTEXT.md
odoo/addons/stock_replenishment_mrp_bom_selection/readme/CONTRIBUTORS.md
odoo/addons/stock_replenishment_mrp_bom_selection/readme/DESCRIPTION.md
odoo/addons/stock_replenishment_mrp_bom_selection/readme/USAGE.md
odoo/addons/stock_replenishment_mrp_bom_selection/security/ir.model.access.csv
odoo/addons/stock_replenishment_mrp_bom_selection/static/description/icon.png
odoo/addons/stock_replenishment_mrp_bom_selection/static/description/index.html
odoo/addons/stock_replenishment_mrp_bom_selection/tests/__init__.py
odoo/addons/stock_replenishment_mrp_bom_selection/tests/test_stock_replenishment_mrp_bom_selection.py
odoo/addons/stock_replenishment_mrp_bom_selection/wizard/__init__.py
odoo/addons/stock_replenishment_mrp_bom_selection/wizard/material_availability_wizard.py
odoo/addons/stock_replenishment_mrp_bom_selection/wizard/material_availability_wizard_views.xml
odoo/addons/stock_replenishment_mrp_bom_selection/wizard/stock_warehouse_orderpoint_replenish_wizard.py
odoo/addons/stock_replenishment_mrp_bom_selection/wizard/stock_warehouse_orderpoint_replenish_wizard_views.xml
odoo_addon_stock_replenishment_mrp_bom_selection-17.0.1.0.0.5.dist-info/METADATA
odoo_addon_stock_replenishment_mrp_bom_selection-17.0.1.0.0.5.dist-info/WHEEL
odoo_addon_stock_replenishment_mrp_bom_selection-17.0.1.0.0.5.dist-info/top_level.txt
odoo_addon_stock_replenishment_mrp_bom_selection-17.0.1.0.0.5.dist-info/RECORD
